PKG-INFO
README.txt
plonetheme.rcom-configure.zcml
pypi_upload.sh
setup.cfg
setup.py
docs/HISTORY.txt
docs/INSTALL.txt
docs/LICENSE.GPL
docs/LICENSE.txt
plonetheme/__init__.py
plonetheme.rcom.egg-info/PKG-INFO
plonetheme.rcom.egg-info/SOURCES.txt
plonetheme.rcom.egg-info/dependency_links.txt
plonetheme.rcom.egg-info/entry_points.txt
plonetheme.rcom.egg-info/namespace_packages.txt
plonetheme.rcom.egg-info/not-zip-safe
plonetheme.rcom.egg-info/requires.txt
plonetheme.rcom.egg-info/top_level.txt
plonetheme/rcom/__init__.py
plonetheme/rcom/configure.zcml
plonetheme/rcom/profiles.zcml
plonetheme/rcom/setuphandlers.py
plonetheme/rcom/skins.zcml
plonetheme/rcom/tests.py
plonetheme/rcom/version.txt
plonetheme/rcom/browser/__init__.py
plonetheme/rcom/browser/configure.zcml
plonetheme/rcom/browser/interfaces.py
plonetheme/rcom/browser/viewlet.pt
plonetheme/rcom/browser/viewlets.py
plonetheme/rcom/browser/images/CONTENT.txt
plonetheme/rcom/browser/images/README.txt
plonetheme/rcom/browser/images/body.jpg
plonetheme/rcom/browser/images/content.jpg
plonetheme/rcom/browser/images/description.jpg
plonetheme/rcom/browser/images/h1.gif
plonetheme/rcom/browser/images/h2.jpg
plonetheme/rcom/browser/images/nav_a_hover.jpg
plonetheme/rcom/browser/images/sidebar.jpg
plonetheme/rcom/browser/images/wrapper2.jpg
plonetheme/rcom/browser/stylesheets/README.txt
plonetheme/rcom/browser/stylesheets/main.css
plonetheme/rcom/browser/templates/news.pt
plonetheme/rcom/profiles/default/cssregistry.xml
plonetheme/rcom/profiles/default/import_steps.xml
plonetheme/rcom/profiles/default/jsregistry.xml
plonetheme/rcom/profiles/default/plonetheme.rcom_various.txt
plonetheme/rcom/profiles/default/skins.xml
plonetheme/rcom/profiles/default/viewlets.xml
plonetheme/rcom/skins/plonetheme_rcom_custom_images/CONTENT.txt
plonetheme/rcom/skins/plonetheme_rcom_custom_images/logo-rcom.jpg
plonetheme/rcom/skins/plonetheme_rcom_custom_images/tagcloud.swf
plonetheme/rcom/skins/plonetheme_rcom_custom_templates/CONTENT.txt
plonetheme/rcom/skins/plonetheme_rcom_custom_templates/main_template.pt
plonetheme/rcom/skins/plonetheme_rcom_styles/CONTENT.txt
plonetheme/rcom/skins/plonetheme_rcom_styles/authoring.css.dtml
plonetheme/rcom/skins/plonetheme_rcom_styles/base.css.dtml
plonetheme/rcom/skins/plonetheme_rcom_styles/base_properties.props
