Metadata-Version: 1.0
Name: plonetheme.rcom
Version: 1.0.0
Summary: An installable theme for Plone 3.0.
Home-page: http://www.rcom.com.ar/
Author: Roman Mottino
Author-email: roman.mottino@rcom.com.ar
License: GPL
Keywords: web zope plone theme
Platform: UNKNOWN
Classifier: Framework :: Plone
Classifier: Framework :: Zope2
Classifier: Framework :: Zope3
Classifier: Programming Language :: Python
Classifier: Topic :: Software Development :: Libraries :: Python Modules
